{
    "Description:": "Plan and direct disaster response or crisis management activities, provide disaster preparedness training, and prepare emergency plans and procedures for natural (e.g., hurricanes, floods, earthquakes), wartime, or technological (e.g., nuclear power plant emergencies or hazardous materials spills) disasters or hostage situations.",
    "Code:": "11-9161.00",
    "Salary:": 86130,
    "Prep:": 4,
    "Education:": [
        "bachelor's degree",
        "master's degree"
    ]
}