{
    "Description:": "Perform administrative and certain clinical duties under the direction of a physician. Administrative duties may include scheduling appointments, maintaining medical records, billing, and coding information for insurance purposes. Clinical duties may include taking and recording vital signs and medical histories, preparing patients for examination, drawing blood, and administering medications as directed by physician.",
    "Code:": "31-9092.00",
    "Salary:": 44200,
    "Prep:": 3,
    "Education:": [
        "certificate after high school",
        "high school diploma/GED"
    ]
}